pytoros/__init__.py
pytoros/token.py
pytoros-0.1.4.dist-info/LICENSE
pytoros-0.1.4.dist-info/METADATA
pytoros-0.1.4.dist-info/WHEEL
pytoros-0.1.4.dist-info/top_level.txt
pytoros-0.1.4.dist-info/RECORD
