Metadata-Version: 2.1
Name: pytoros
Version: 0.1.4
Summary: Download leveraged token data from Toros Finance.
Author-email: Mohammed Faheem <mohdfaheem.1205@gmail.com>, Dhruvan Gnanadhandayuthapani <dhruvan2006@gmail.com>
Project-URL: source, https://github.com/dhruvan2006/pytoros
Keywords: leverage,toros,crypto
Classifier: Development Status :: 4 - Beta
Classifier: License :: OSI Approved :: MIT License
Classifier: Programming Language :: Python :: 3.7
Classifier: Programming Language :: Python :: 3.8
Classifier: Programming Language :: Python :: 3.9
Requires-Python: >=3.7
License-File: LICENSE
Requires-Dist: requests
Requires-Dist: pandas
